eastr-1.1.2.dist-info/RECORD
eastr-1.1.2.dist-info/LICENSE
eastr-1.1.2.dist-info/WHEEL
eastr-1.1.2.dist-info/entry_points.txt
eastr-1.1.2.dist-info/top_level.txt
eastr-1.1.2.dist-info/METADATA
eastr/junction_extractor
eastr/vacuum
eastr/output_utils.py
eastr/alignment_utils.py
eastr/__init__.py
eastr/extract_junctions.py
eastr/utils.py
eastr/get_spurious_introns.py
eastr/run_eastr.py
