Metadata-Version: 2.2
Name: eastr
Version: 1.1.2
Summary: Tool for emending alignments of spuriously spliced transcript reads
Home-page: https://github.com/ishinder/EASTR
Author: Ida Shinder
Author-email: ishinde1@jhmi.edu
License: MIT
Requires-Python: >=3.10
License-File: LICENSE
Requires-Dist: biopython<2.0,>=1.81
Requires-Dist: mappy<3.0,>=2.26
Requires-Dist: numpy>=1.26.1
Requires-Dist: pandas<2.3,>=2.1.2
Requires-Dist: pysam<0.23,>=0.22.0
Dynamic: author
Dynamic: author-email
Dynamic: description
Dynamic: description-content-type
Dynamic: home-page
Dynamic: license
Dynamic: requires-dist
Dynamic: requires-python
Dynamic: summary
